Metadata-Version: 1.1
Name: secret-keeper
Version: 0.2.0
Summary: Secret Keeper
Home-page: https://github.com/ridi/secret-keeper-python
Author: UNKNOWN
Author-email: UNKNOWN
License: UNKNOWN
Keywords: secret,secret-keeper,ridi,ridibooks
Platform: UNKNOWN
Classifier: License :: OSI Approved :: MIT License
Classifier: Programming Language :: Python :: 3
